{
  "bindobjects": [
    {
      "name": "ec_household",
      "columns": [
        {
          "column_name": "base_entity_id",
          "type": "Client",
          "json_mapping": {
            "field": "baseEntityId"
          }
        },
        {
          "column_name": "FWGOBHHID",
          "type": "Client",
          "json_mapping": {
            "field": "attributes.GoB_HHID"
          }
        },
        {
          "column_name": "FWJIVHHID",
          "type": "Client",
          "json_mapping": {
            "field": "attributes.JiVitA_HHID"
          }
        },
        {
          "column_name": "existing_Mauzapara",
          "type": "Client",
          "json_mapping": {
            "field": "adresses.address4"
          }
        },
        {
          "column_name": "FWHOHFNAME",
          "type": "Client",
          "json_mapping": {
            "field": "firstName"
          }
        },
        {
          "column_name": "FWNHREGDATE",
          "type": "Event",
          "json_mapping": {
            "field": "obs.fieldCode",
            "concept": "160753AAAAAAAAAAAAAAAAAAAAAAAAAAAAAA"
          }
        },
        {
          "column_name": "FWCENDATE",
          "type": "Event",
          "json_mapping": {
            "field": "obs.fieldCode",
            "concept": "160753AAAAAAAAAAAAAAAAAAAAAAAAAAAAAA"
          }
        }
      ]
    },
    {
      "name": "ec_elco",
      "columns": [
        {
          "column_name": "base_entity_id",
          "type": "Client",
          "json_mapping": {
            "field": "baseEntityId"
          }
        },
        {
          "column_name": "relational_id",
          "type": "Client",
          "json_mapping": {
            "field": "relationships.householdHead"
          }
        },
        {
          "column_name": "GOBHHID",
          "type": "Client",
          "json_mapping": {
            "field": "attributes.GoB_HHID"
          }
        },
        {
          "column_name": "JiVitAHHID",
          "type": "Client",
          "json_mapping": {
            "field": "attributes.JiVitA_HHID"
          }
        },
        {
          "column_name": "FWWOMFNAME",
          "type": "Client",
          "json_mapping": {
            "field": "firstName"
          }
        },
        {
          "column_name": "FWHUSNAME",
          "type": "Event",
          "json_mapping": {
            "field": "obs.fieldCode",
            "concept": "161135AAAAAAAAAAAAAAAAAAAAAAAAAAAAAA"
          }
        },
        {
          "column_name": "FWWOMMAUZA_PARA",
          "type": "Client",
          "json_mapping": {
            "field": "adresses.address4"
          }
        },
        {
          "column_name": "FWWOMAGE",
          "type": "Event",
          "json_mapping": {
            "field": "obs.fieldCode",
            "concept": "1532AAAAAAAAAAAAAAAAAAAAAAAAAAAAAAAA"
          }
        },
        {
          "column_name": "FWPSRDATE",
          "type": "Event",
          "json_mapping": {
            "field": "obs.fieldCode",
            "concept": "160753AAAAAAAAAAAAAAAAAAAAAAAAAAAAAA"
          }
        },
        {
          "column_name": "FWPSRPREGSTS",
          "type": "Event",
          "json_mapping": {
            "field": "obs.fieldCode",
            "concept": "162942AAAAAAAAAAAAAAAAAAAAAAAAAAAAAA"
          }
        },
        {
          "column_name": "FWWOMNID",
          "type": "Client",
          "json_mapping": {
            "field": "identifiers.NID"
          }
        },
        {
          "column_name": "FWWOMBID",
          "type": "Client",
          "json_mapping": {
            "field": "identifiers.Birth Registration ID"
          }
        },
        {
          "column_name": "WomanREGDATE",
          "type": "Client",
          "json_mapping": {
            "field": "dateCreated",
            "comment": "This value should come from the Woman REGDATE but currently it doesn't have a concept mapping"
          }
        }
      ]
    },
    {
      "name": "ec_mcaremother",
      "columns": [
        {
          "column_name": "base_entity_id",
          "type": "Client",
          "json_mapping": {
            "field": "baseEntityId"
          }
        },
        {
          "column_name": "FWPSRLMP",
          "type": "Event",
          "json_mapping": {
            "field": "obs.fieldCode",
            "concept": "1427AAAAAAAAAAAAAAAAAAAAAAAAAAAAAAAA"
          }
        },
        {
          "column_name": "FWVG",
          "type": "Event",
          "json_mapping": {
            "field": "obs.fieldCode",
            "concept": "163090AAAAAAAAAAAAAAAAAAAAAAAAAAAAAA"
          }
        },
        {
          "column_name": "FWHRP",
          "type": "Event",
          "json_mapping": {
            "field": "obs.fieldCode",
            "concept": "163092AAAAAAAAAAAAAAAAAAAAAAAAAAAAAA"
          }
        },
        {
          "column_name": "FWHR_PSR",
          "type": "Event",
          "json_mapping": {
            "field": "obs.fieldCode",
            "concept": "163091AAAAAAAAAAAAAAAAAAAAAAAAAAAAAA"
          }
        },
        {
          "column_name": "FWANC1DATE",
          "type": "Event",
          "json_mapping": {
            "field": "obs.fieldCode",
            "event_type": "ANC Reminder Visit 1",
            "concept": "160753AAAAAAAAAAAAAAAAAAAAAAAAAAAAAA"
          }
        },
        {
          "column_name": "FWANC2DATE",
          "type": "Event",
          "json_mapping": {
            "field": "obs.fieldCode",
            "event_type": "ANC Reminder Visit 2",
            "concept": "160753AAAAAAAAAAAAAAAAAAAAAAAAAAAAAA"
          }
        },
        {
          "column_name": "FWANC3DATE",
          "type": "Event",
          "json_mapping": {
            "field": "obs.fieldCode",
            "event_type": "ANC Reminder Visit 3",
            "concept": "160753AAAAAAAAAAAAAAAAAAAAAAAAAAAAAA"
          }
        },
        {
          "column_name": "FWANC4DATE",
          "type": "Event",
          "json_mapping": {
            "field": "obs.fieldCode",
            "event_type": "ANC Reminder Visit 4",
            "concept": "160753AAAAAAAAAAAAAAAAAAAAAAAAAAAAAA"
          }
        }
      ]
    },
    {
      "name": "ec_pnc",
      "columns": [
        {
          "column_name": "base_entity_id",
          "type": "Client",
          "json_mapping": {
            "field": "baseEntityId"
          }
        },
        {
          "column_name": "FWBNFDTOO",
          "type": "Event",
          "json_mapping": {
            "field": "obs.fieldCode",
            "concept": "5599AAAAAAAAAAAAAAAAAAAAAAAAAAAAAAAA"
          }
        },
        {
          "column_name": "FWBNFSTS",
          "type": "Event",
          "json_mapping": {
            "field": "obs.fieldCode",
            "concept": "161641AAAAAAAAAAAAAAAAAAAAAAAAAAAAAA"
          }
        },
        {
          "column_name": "FWWOMNID",
          "type": "Client",
          "json_mapping": {
            "field": "identifiers.NID"
          }
        },
        {
          "column_name": "FWVG",
          "type": "Event",
          "json_mapping": {
            "field": "obs.fieldCode",
            "concept": "163090AAAAAAAAAAAAAAAAAAAAAAAAAAAAAA"
          }
        },
        {
          "column_name": "FWHRP",
          "type": "Event",
          "json_mapping": {
            "field": "obs.fieldCode",
            "concept": "163092AAAAAAAAAAAAAAAAAAAAAAAAAAAAAA"
          }
        },
        {
          "column_name": "FWHR_PSR",
          "type": "Event",
          "json_mapping": {
            "field": "obs.fieldCode",
            "concept": "163091AAAAAAAAAAAAAAAAAAAAAAAAAAAAAA"
          }
        },
        {
          "column_name": "FWPNC1DATE",
          "type": "Event",
          "json_mapping": {
            "field": "obs.fieldCode",
            "event_type": "PNC Reminder Visit 1",
            "concept": "160753AAAAAAAAAAAAAAAAAAAAAAAAAAAAAA"
          }
        },
        {
          "column_name": "FWPNC2DATE",
          "type": "Event",
          "json_mapping": {
            "field": "obs.fieldCode",
            "event_type": "PNC Reminder Visit 2",
            "concept": "160753AAAAAAAAAAAAAAAAAAAAAAAAAAAAAA"
          }
        },
        {
          "column_name": "FWPNC3DATE",
          "type": "Event",
          "json_mapping": {
            "field": "obs.fieldCode",
            "event_type": "PNC Reminder Visit 3",
            "concept": "160753AAAAAAAAAAAAAAAAAAAAAAAAAAAAAA"
          }
        }
      ]
    },
    {
      "name": "ec_mcarechild",
      "columns": [
        {
          "column_name": "base_entity_id",
          "type": "Client",
          "json_mapping": {
            "field": "baseEntityId"
          }
        },
        {
          "column_name": "relational_id",
          "type": "Client",
          "json_mapping": {
            "field": "relationships.mother"
          }
        },
        {
          "column_name": "FWBNFDTOO",
          "type": "Client",
          "json_mapping": {
            "field": "birthdate"
          }
        },
        {
          "column_name": "FWBNFCHLDVITSTS",
          "type": "Event",
          "json_mapping": {
            "field": "obs.fieldCode",
            "concept": "159926AAAAAAAAAAAAAAAAAAAAAAAAAA"
          }
        },
        {
          "column_name": "FWBNFGEN",
          "type": "Event",
          "json_mapping": {
            "field": "obs.fieldCode",
            "concept": "1587AAAAAAAAAAAAAAAAAAAAAAAAAAAA"
          }
        },
        {
          "column_name": "FWENC1DATE",
          "type": "Event",
          "json_mapping": {
            "field": "obs.fieldCode",
            "event_type": "Essential Newborn Care 1",
            "concept": "160753AAAAAAAAAAAAAAAAAAAAAAAAAA"
          }
        },
        {
          "column_name": "FWENC2DATE",
          "type": "Event",
          "json_mapping": {
            "field": "obs.fieldCode",
            "event_type": "Essential Newborn Care 2",
            "concept": "160753AAAAAAAAAAAAAAAAAAAAAAAAAA"
          }
        },
        {
          "column_name": "FWENC3DATE",
          "type": "Event",
          "json_mapping": {
            "field": "obs.fieldCode",
            "event_type": "Essential Newborn Care 3",
            "concept": "160753AAAAAAAAAAAAAAAAAAAAAAAAAA"
          }
        }
      ]
    }
  ]
}