[
    {
        "parent":"bidan",
        "child":"ibu",
        "field":"ibu_ibu",
        "kind":"one_to_many",
        "from":"bidan.id",
        "to":"ibu.relationalid"
    },
    {
        "parent":"kartu_ibu",
        "child": "ibu",
        "field":"istri",
        "kind":"one_to_one",
        "from":"kartu_ibu.id",
        "to":"ibu.relationalid"
    },
    {
        "parent":"ibu",
        "child":"anak",
        "field":"anak_anak",
        "kind":"one_to_many",
        "from":"ibu.id",
        "to":"anak.relationalid"
    }
]